agent_framework_ag_ui/__init__.py
agent_framework_ag_ui/_agent.py
agent_framework_ag_ui/_client.py
agent_framework_ag_ui/_endpoint.py
agent_framework_ag_ui/_event_converters.py
agent_framework_ag_ui/_http_service.py
agent_framework_ag_ui/_message_adapters.py
agent_framework_ag_ui/_run.py
agent_framework_ag_ui/_types.py
agent_framework_ag_ui/_utils.py
agent_framework_ag_ui/py.typed
agent_framework_ag_ui/_orchestration/__init__.py
agent_framework_ag_ui/_orchestration/_helpers.py
agent_framework_ag_ui/_orchestration/_predictive_state.py
agent_framework_ag_ui/_orchestration/_tooling.py
agent_framework_ag_ui_examples/.env.example
agent_framework_ag_ui_examples/README.md
agent_framework_ag_ui_examples/__init__.py
agent_framework_ag_ui_examples/__main__.py
agent_framework_ag_ui_examples/.vscode/settings.json
agent_framework_ag_ui_examples/agents/__init__.py
agent_framework_ag_ui_examples/agents/document_writer_agent.py
agent_framework_ag_ui_examples/agents/human_in_the_loop_agent.py
agent_framework_ag_ui_examples/agents/recipe_agent.py
agent_framework_ag_ui_examples/agents/research_assistant_agent.py
agent_framework_ag_ui_examples/agents/simple_agent.py
agent_framework_ag_ui_examples/agents/task_planner_agent.py
agent_framework_ag_ui_examples/agents/task_steps_agent.py
agent_framework_ag_ui_examples/agents/ui_generator_agent.py
agent_framework_ag_ui_examples/agents/weather_agent.py
agent_framework_ag_ui_examples/server/__init__.py
agent_framework_ag_ui_examples/server/main.py
agent_framework_ag_ui_examples/server/api/backend_tool_rendering.py
agent_framework_ag_ui-1.0.0b260130.dist-info/METADATA
agent_framework_ag_ui-1.0.0b260130.dist-info/WHEEL
agent_framework_ag_ui-1.0.0b260130.dist-info/licenses/LICENSE
agent_framework_ag_ui-1.0.0b260130.dist-info/RECORD
