Metadata-Version: 2.4
Name: agent-framework-ag-ui
Version: 1.0.0b260130
Summary: AG-UI protocol integration for Agent Framework
Project-URL: homepage, https://aka.ms/agent-framework
Project-URL: source, https://github.com/microsoft/agent-framework/tree/main/python
Project-URL: release_notes, https://github.com/microsoft/agent-framework/releases?q=tag%3Apython-1&expanded=true
Project-URL: issues, https://github.com/microsoft/agent-framework/issues
Author-email: Microsoft <af-support@microsoft.com>
License-File: LICENSE
Classifier: Development Status :: 4 - Beta
Classifier: Intended Audience :: Developers
Classifier: License :: OSI Approved :: MIT License
Classifier: Programming Language :: Python :: 3
Classifier: Programming Language :: Python :: 3.10
Classifier: Programming Language :: Python :: 3.11
Classifier: Programming Language :: Python :: 3.12
Classifier: Programming Language :: Python :: 3.13
Classifier: Typing :: Typed
Requires-Python: >=3.10
Requires-Dist: ag-ui-protocol>=0.1.9
Requires-Dist: agent-framework-core
Requires-Dist: fastapi>=0.115.0
Requires-Dist: uvicorn>=0.30.0
Provides-Extra: dev
Requires-Dist: httpx>=0.27.0; extra == 'dev'
Requires-Dist: pytest-asyncio>=0.24.0; extra == 'dev'
Requires-Dist: pytest>=8.0.0; extra == 'dev'
